python_array
