Metadata-Version: 1.2
Name: python-array
Version: 0.1.1
Summary: https://python-utilities.readthedocs.io/en/latest/array.html
Home-page: https://github.com/shawwn/python-array
Author: Shawn Presser
Author-email: shawnpresser@gmail.com
Maintainer: Shawn Presser
Maintainer-email: shawnpresser@gmail.com
License: UNKNOWN
Platform: UNKNOWN
Requires-Python: >=3.6,<4.0
